mlendpoints/__init__.py
mlendpoints/__version__.py
mlendpoints/client.py
mlendpoints/communication.py
mlendpoints/server.py
mlendpoints-0.1.8.dist-info/METADATA
mlendpoints-0.1.8.dist-info/RECORD
mlendpoints-0.1.8.dist-info/WHEEL
mlendpoints-0.1.8.dist-info/top_level.txt
